nester.py
The_nester-1.0.1.dist-info/METADATA
The_nester-1.0.1.dist-info/WHEEL
The_nester-1.0.1.dist-info/top_level.txt
The_nester-1.0.1.dist-info/RECORD
