Metadata-Version: 2.1
Name: The-nester
Version: 1.0.1
Summary: A simple function to display nested lists
Home-page: http://www.sir-bron.com
Author: lebrone
Author-email: musirzx@gmail.com
License: UNKNOWN
Platform: UNKNOWN
